[
  {
    "pdfUrl": "https://fresh-teacher.github.io/s2-past-papers/ENT GUIDE S.2.pdf"
},
{
    "pdfUrl": "https://fresh-teacher.github.io/s2-past-papers/ENT S.2 SAMPLE FOR  END OF YEAR .pdf"
},
{
    "pdfUrl": "https://fresh-teacher.github.io/s2-past-papers/ent s2 end of term 2 2022.docx"
},
{
    "pdfUrl": "https://fresh-teacher.github.io/s2-past-papers/ENT S2.pdf"
},
{
    "pdfUrl": "https://fresh-teacher.github.io/s2-past-papers/Entebbe UCE CHEM P2.pdf"
},
{
    "pdfUrl": "https://fresh-teacher.github.io/s2-past-papers/Entrep S.2 exams.pdf"
},
{
    "pdfUrl": "https://fresh-teacher.github.io/s2-past-papers/S.2 End of Year.docx"
},
{
    "pdfUrl": "https://fresh-teacher.github.io/s2-past-papers/S.2 ENT end of term 1 2024.docx"
},
{
    "pdfUrl": "https://fresh-teacher.github.io/s2-past-papers/S.2 ENT end.docx"
},
{
    "pdfUrl": "https://fresh-teacher.github.io/s2-past-papers/S.2 ENT TERM 2 2024.docx"
},
{
    "pdfUrl": "https://fresh-teacher.github.io/s2-past-papers/S.2 eot 1.docx"
},
{
    "pdfUrl": "https://fresh-teacher.github.io/s2-past-papers/S.2 EOT 3 2023.pdf"
},
{
    "pdfUrl": "https://fresh-teacher.github.io/s2-past-papers/S.2-ENTREPREURSHIP-EXAM.pdf"
},
{
    "pdfUrl": "https://fresh-teacher.github.io/s2-past-papers/S.2EOT1.docx"
},
{
    "pdfUrl": "https://fresh-teacher.github.io/s2-past-papers/S2 ENGLISH LANGUAGE KAMSSA  EXAMINATIONS.pdf"
},
{
    "pdfUrl": "https://fresh-teacher.github.io/s2-past-papers/S2 ENT END OF YEAR ASSESSEMRNT 2023.pdf"
},
{
    "pdfUrl": "https://fresh-teacher.github.io/s2-past-papers/S2 ENTREPRENEURSHIP EDUCATION.pdf"
},
{
    "pdfUrl": "https://fresh-teacher.github.io/s2-past-papers/senior two entrepreneurship.pdf"
},
    {
      "title": "",
      "description": "Senior Two",
      "price": 5000,
      "pdfUrl": "https://fresh-teacher.github.io/s2/ENT S2-1.pdf"
      },
      {
        "title": "",
        "description": "Senior Two",
        "price": 5000,
        "pdfUrl": "https://fresh-teacher.github.io/s2/Entebbe UCE CHEM P2.pdf"
      },
      {
        "title": "",
        "description": "Senior Two",
        "price": 5000,
        "pdfUrl": "https://fresh-teacher.github.io/s2/S.2-ENTREPREURSHIP-EXAM.pdf"
      },
      {
        "title": "",
        "description": "Senior Two",
        "price": 5000,
        "pdfUrl": "https://fresh-teacher.github.io/s2/S2 ENT END OF YEAR ASSESSEMRNT 2023.pdf"
      },
      {
        "title": "",
        "description": "Senior Two",
        "price": 5000,
        "pdfUrl": "https://fresh-teacher.github.io/s2/S2 ENTREPRENEURSHIP EDUCATION.pdf"
      },
      {
        "title": "",
        "description": "Senior Two",
        "price": 5000,
        "pdfUrl": "https://fresh-teacher.github.io/s2/senior two entrepreneurship.pdf"
      },
      {
        "title": "",
        "description": "Senior Two",
        "price": 5000,
        "pdfUrl": "https://fresh-teacher.github.io/s2/ENT GUIDE S.2.pdf"
      },
      {
        "title": "",
        "description": "Senior Two",
        "price": 5000,
        "pdfUrl": "https://fresh-teacher.github.io/s2/ENT S.2 SAMPLE FOR  END OF YEAR .pdf"
      },
      {
        "title": "",
        "description": "Senior Two",
        "price": 5000,
        "pdfUrl": "https://fresh-teacher.github.io/s2/ENT S2.pdf"
      }
    ]