[
    {
        "pdfUrl": "https://fresh-teacher.github.io/top-class-past-papers/EOT III TOP LA3.pdf"
    },
    {
        "pdfUrl": "https://fresh-teacher.github.io/top-class-past-papers/PEARL EXAMS TOP LA3 END II.pdf"
    },
    {
        "pdfUrl": "https://fresh-teacher.github.io/top-class-past-papers/TOP LA 3 MID III.pdf"
    },
    {
        "pdfUrl": "https://fresh-teacher.github.io/top-class-past-papers/TOP LA.3.pdf"
    },
    {
        "pdfUrl": "https://fresh-teacher.github.io/top-class-past-papers/TOP LA3 END III-1.docx"
    },
    {
        "pdfUrl": "https://fresh-teacher.github.io/top-class-past-papers/TOP LA3 END III-1.pdf"
    },
    {
        "pdfUrl": "https://fresh-teacher.github.io/top-class-past-papers/TOP LA3 END III-2.docx"
    },
    {
        "pdfUrl": "https://fresh-teacher.github.io/top-class-past-papers/TOP LA3 END III-2.pdf"
    },
    {
        "pdfUrl": "https://fresh-teacher.github.io/top-class-past-papers/TOP LA3 END III-3.docx"
    },
    {
        "pdfUrl": "https://fresh-teacher.github.io/top-class-past-papers/TOP LA3 END III.docx"
    },
    {
        "pdfUrl": "https://fresh-teacher.github.io/top-class-past-papers/TOP LA3 END III.pdf"
    }
]